<?xml version="1.0" encoding="UTF-8" ?>	
<!DOCTYPE suite SYSTEM "http://testng.org/testng-1.0.dtd">
<suite name="Suite">
	<test name="VideoTap">

		<classes>
		
			
		<!-- 
			<class name="testScript.DRLoginTest">
				<methods>
					<include name= "browserSetUp" />
					<include name= "vtapLogin" />
				</methods>
			</class>
			
			<class name="testScript.CreateVODProject">
				<methods>
					<include name= "browserSetUp" />
					<include name= "DesignProject" />
					<include name= "CreateNewProjectFunc" />
					<include name= "AddNamefieldFunc" />
					<include name= "AddLanguageFunc" />
					<include name= "ContentSelectFunc" />
					<include name= "GenreSelectFunc" />
					<include name= "AddThumbnailFunc" />
					<include name= "AddVideoMediaFunc" />
					<include name= "AddTags" />
					<include name= "ClickNextFunc" />
					<include name= "ClickCreateFunc" />
					<include name= "WaitForElement" />
					<include name= "closewebBrowser" />
				</methods>
			</class>
		 -->
		
			<class name="testScript.EditVODProject">
				<methods>
					<include name="browserSetUp" />
					<include name="OpenProject" />
					<include name="EditSuiteFunc" />
					<include name="AddButtonFunc" />
					<include name="AddFormFunc" />
					<include name="AddTextFunc" />
					<include name="AddImageFunc" />
					<include name="AddTimerFunc" />
					<include name="AddMenuFunc" />
					<include name="AddArrowFunc" />
					<include name="AddLineFunc" />
					<include name="AddSRQquestion" />
					<include name="AddMRQquestion" />
					<include name="AddMatchTheFollowingQuestion" />
					<include name="AddSequenceQuestion" />
					<include name="AddFillBlankQuestion" />
					<include name="TriggerFunction" />
					<include name="ArrangementFunction" />
					<exclude name="UploadFileFromDrive" />
					<include name= "closewebBrowser" />
					
				</methods>
			</class>
		</classes>
	</test>
</suite>	